{ "backgroundcolor":"#494a49",
 "compressionlevel":-1,
 "height":20,
 "infinite":false,
 "layers":[
        {
         "data":[0, 0, 0, 0, 0, 0, 0, 0, 0, 0, 0, 0, 0, 0, 0, 143, 0, 0, 0, 0, 0, 0, 0, 0, 0,
            0, 0, 0, 0, 0, 0, 0, 0, 0, 0, 0, 0, 0, 0, 0, 0, 0, 0, 0, 0, 0, 0, 0, 0, 0,
            0, 0, 0, 0, 0, 0, 68, 69, 69, 69, 144, 0, 0, 0, 0, 0, 0, 0, 0, 0, 145, 146, 0, 0, 146,
            0, 0, 0, 0, 0, 0, 0, 0, 0, 0, 138, 144, 0, 0, 0, 0, 0, 0, 0, 145, 139, 133, 0, 0, 133,
            0, 0, 0, 0, 0, 0, 0, 0, 0, 0, 0, 138, 144, 0, 0, 0, 0, 0, 145, 139, 0, 133, 0, 0, 133,
            0, 0, 0, 0, 0, 0, 0, 0, 0, 0, 0, 0, 138, 147, 147, 147, 147, 147, 139, 0, 0, 133, 0, 0, 133,
            69, 69, 69, 69, 69, 69, 70, 0, 0, 0, 0, 0, 0, 0, 0, 0, 0, 0, 0, 0, 0, 133, 0, 0, 133,
            0, 0, 0, 0, 0, 0, 0, 0, 0, 0, 0, 0, 0, 0, 0, 0, 0, 0, 0, 0, 0, 133, 147, 147, 133,
            0, 0, 0, 0, 0, 0, 0, 0, 0, 0, 0, 0, 0, 0, 0, 0, 0, 0, 0, 0, 0, 0, 0, 0, 0,
            0, 0, 0, 0, 0, 0, 0, 0, 0, 0, 0, 0, 0, 0, 0, 0, 0, 0, 0, 0, 0, 0, 0, 0, 0,
            0, 0, 0, 0, 0, 0, 0, 0, 0, 0, 0, 0, 0, 0, 0, 0, 0, 0, 0, 0, 0, 0, 0, 0, 0,
            0, 0, 0, 0, 0, 0, 0, 0, 0, 0, 0, 0, 0, 0, 0, 0, 0, 0, 0, 0, 0, 0, 0, 0, 0,
            0, 0, 0, 0, 0, 0, 0, 0, 0, 0, 0, 0, 0, 0, 0, 0, 0, 0, 0, 0, 0, 0, 0, 0, 0,
            0, 0, 0, 0, 0, 0, 0, 0, 0, 0, 0, 0, 0, 0, 0, 0, 0, 0, 0, 0, 0, 0, 0, 0, 0,
            0, 0, 0, 0, 0, 0, 0, 0, 0, 0, 0, 0, 0, 0, 0, 0, 0, 0, 0, 0, 0, 0, 0, 0, 0,
            0, 0, 0, 0, 0, 0, 0, 0, 0, 0, 0, 0, 0, 0, 0, 0, 0, 0, 0, 0, 0, 0, 0, 0, 0,
            55, 55, 55, 55, 55, 55, 55, 0, 0, 0, 0, 0, 0, 0, 0, 0, 0, 0, 0, 0, 0, 0, 0, 0, 0,
            0, 0, 0, 0, 0, 0, 0, 0, 0, 0, 0, 0, 0, 0, 0, 0, 0, 0, 0, 0, 0, 0, 0, 0, 0,
            0, 0, 0, 0, 0, 0, 0, 0, 0, 0, 0, 0, 0, 0, 0, 0, 0, 0, 0, 0, 0, 0, 0, 0, 0,
            0, 0, 0, 0, 0, 0, 0, 0, 0, 0, 0, 0, 0, 0, 0, 0, 0, 0, 0, 0, 0, 0, 0, 0, 0],
         "height":20,
         "id":1,
         "name":"Platforms",
         "opacity":1,
         "type":"tilelayer",
         "visible":true,
         "width":25,
         "x":0,
         "y":0
        }, 
        {
         "draworder":"topdown",
         "id":11,
         "name":"End Level",
         "objects":[
                {
                 "gid":149,
                 "height":128,
                 "id":16,
                 "name":"",
                 "rotation":0,
                 "type":"",
                 "visible":true,
                 "width":128,
                 "x":2887.61290322581,
                 "y":899.483870967742
                }],
         "opacity":1,
         "type":"objectgroup",
         "visible":true,
         "x":0,
         "y":0
        }, 
        {
         "draworder":"topdown",
         "id":12,
         "name":"Objective",
         "objects":[
                {
                 "gid":167,
                 "height":128,
                 "id":13,
                 "name":"",
                 "rotation":0,
                 "type":"",
                 "visible":true,
                 "width":128,
                 "x":2505.77299880526,
                 "y":1544.64516129032
                }, 
                {
                 "gid":167,
                 "height":128,
                 "id":14,
                 "name":"",
                 "rotation":0,
                 "type":"",
                 "visible":true,
                 "width":128,
                 "x":0.516129032258064,
                 "y":760.774193548387
                }, 
                {
                 "gid":167,
                 "height":128,
                 "id":15,
                 "name":"",
                 "rotation":0,
                 "type":"",
                 "visible":true,
                 "width":128,
                 "x":894.064516129032,
                 "y":276.903225806452
                }],
         "opacity":1,
         "type":"objectgroup",
         "visible":true,
         "x":0,
         "y":0
        }, 
        {
         "draworder":"topdown",
         "id":2,
         "name":"Player",
         "objects":[],
         "opacity":1,
         "type":"objectgroup",
         "visible":true,
         "x":0,
         "y":0
        }, 
        {
         "draworder":"topdown",
         "id":4,
         "name":"Power Up",
         "objects":[
                {
                 "gid":153,
                 "height":128,
                 "id":18,
                 "name":"",
                 "properties":[
                        {
                         "name":"type",
                         "type":"string",
                         "value":"health"
                        }],
                 "rotation":0,
                 "type":"",
                 "visible":true,
                 "width":128,
                 "x":639.225806451613,
                 "y":2047.87096774194
                }],
         "opacity":1,
         "properties":[
                {
                 "name":"type",
                 "type":"string",
                 "value":"Invincible"
                }],
         "type":"objectgroup",
         "visible":true,
         "x":0,
         "y":0
        }, 
        {
         "data":[0, 0, 0, 0, 0, 0, 0, 0, 0, 0, 0, 0, 0, 0, 0, 0, 0, 0, 0, 0, 0, 0, 0, 0, 0,
            0, 0, 0, 0, 0, 0, 0, 0, 0, 0, 0, 0, 0, 0, 0, 0, 0, 0, 0, 0, 0, 0, 0, 0, 0,
            0, 0, 0, 0, 0, 0, 0, 0, 0, 0, 0, 0, 0, 0, 0, 0, 0, 0, 0, 0, 0, 0, 0, 0, 0,
            0, 0, 0, 0, 0, 0, 0, 0, 0, 0, 0, 0, 0, 0, 0, 0, 0, 0, 0, 0, 0, 0, 0, 0, 0,
            0, 0, 0, 0, 0, 0, 0, 0, 0, 0, 0, 0, 0, 0, 0, 0, 0, 0, 0, 0, 0, 0, 0, 0, 0,
            0, 0, 0, 0, 0, 0, 0, 0, 0, 0, 0, 0, 0, 0, 0, 0, 0, 0, 0, 0, 0, 0, 0, 0, 0,
            0, 0, 0, 0, 0, 0, 0, 0, 0, 0, 0, 0, 0, 0, 0, 0, 0, 0, 0, 0, 0, 0, 0, 0, 0,
            0, 0, 0, 0, 0, 0, 0, 0, 0, 0, 0, 0, 0, 0, 0, 0, 0, 0, 0, 0, 0, 0, 0, 0, 0,
            0, 0, 0, 0, 0, 0, 0, 0, 0, 0, 0, 0, 0, 0, 0, 0, 0, 0, 0, 0, 0, 0, 0, 0, 0,
            0, 0, 0, 0, 0, 0, 0, 0, 0, 0, 0, 0, 0, 0, 0, 0, 0, 0, 0, 0, 0, 0, 0, 0, 0,
            0, 0, 0, 0, 0, 0, 0, 0, 0, 0, 0, 0, 0, 0, 0, 0, 0, 0, 0, 0, 0, 0, 0, 0, 0,
            0, 0, 0, 0, 0, 0, 0, 0, 0, 0, 0, 0, 0, 0, 0, 0, 0, 0, 0, 0, 0, 0, 0, 0, 0,
            0, 0, 0, 0, 0, 0, 0, 0, 0, 0, 0, 0, 0, 0, 0, 0, 0, 0, 0, 0, 0, 0, 0, 0, 0,
            0, 0, 0, 0, 0, 0, 0, 0, 0, 0, 0, 0, 0, 0, 0, 0, 0, 0, 0, 0, 0, 0, 0, 0, 0,
            0, 0, 0, 0, 0, 0, 0, 0, 0, 0, 0, 0, 0, 0, 0, 0, 0, 0, 0, 0, 0, 0, 0, 0, 0,
            0, 0, 0, 0, 0, 0, 0, 0, 0, 0, 0, 0, 0, 0, 0, 0, 0, 0, 0, 0, 0, 0, 0, 0, 0,
            0, 0, 0, 0, 0, 0, 0, 0, 0, 0, 0, 0, 0, 0, 0, 0, 0, 0, 0, 0, 0, 0, 0, 0, 0,
            0, 0, 0, 0, 0, 0, 0, 0, 0, 0, 0, 0, 0, 0, 0, 0, 0, 0, 0, 0, 0, 0, 0, 0, 0,
            49, 49, 49, 49, 49, 49, 49, 49, 49, 49, 49, 49, 49, 49, 49, 49, 49, 49, 49, 49, 49, 49, 49, 49, 49,
            48, 48, 48, 48, 48, 48, 48, 48, 48, 48, 48, 48, 48, 48, 48, 48, 48, 48, 48, 48, 48, 48, 48, 48, 48],
         "height":20,
         "id":3,
         "name":"Don't Touch",
         "opacity":1,
         "type":"tilelayer",
         "visible":true,
         "width":25,
         "x":0,
         "y":0
        }, 
        {
         "draworder":"topdown",
         "id":5,
         "name":"Enemies",
         "objects":[
                {
                 "height":0,
                 "id":6,
                 "name":"",
                 "point":true,
                 "properties":[
                        {
                         "name":"Points",
                         "type":"int",
                         "value":50
                        }, 
                        {
                         "name":"boundary_left",
                         "type":"int",
                         "value":1
                        }, 
                        {
                         "name":"boundary_right",
                         "type":"int",
                         "value":400
                        }, 
                        {
                         "name":"change_x",
                         "type":"float",
                         "value":1
                        }, 
                        {
                         "name":"type",
                         "type":"string",
                         "value":"zombie"
                        }],
                 "rotation":0,
                 "type":"",
                 "visible":true,
                 "width":0,
                 "x":321.130378933847,
                 "y":700.064226075787
                }, 
                {
                 "height":0,
                 "id":21,
                 "name":"",
                 "point":true,
                 "properties":[
                        {
                         "name":"Points",
                         "type":"int",
                         "value":500
                        }, 
                        {
                         "name":"boundary_left",
                         "type":"int",
                         "value":850
                        }, 
                        {
                         "name":"boundary_right",
                         "type":"int",
                         "value":1125
                        }, 
                        {
                         "name":"change_x",
                         "type":"float",
                         "value":1
                        }, 
                        {
                         "name":"type",
                         "type":"string",
                         "value":"super zombie"
                        }],
                 "rotation":0,
                 "type":"",
                 "visible":true,
                 "width":0,
                 "x":1983.87096774194,
                 "y":445.161290322581
                }],
         "opacity":1,
         "type":"objectgroup",
         "visible":true,
         "x":0,
         "y":0
        }, 
        {
         "draworder":"topdown",
         "id":6,
         "name":"Bullets",
         "objects":[],
         "opacity":1,
         "type":"objectgroup",
         "visible":true,
         "x":0,
         "y":0
        }, 
        {
         "draworder":"topdown",
         "id":7,
         "name":"Moving Platforms",
         "objects":[
                {
                 "gid":143,
                 "height":128,
                 "id":22,
                 "name":"",
                 "properties":[
                        {
                         "name":"boundary_bottom",
                         "type":"float",
                         "value":5
                        }, 
                        {
                         "name":"boundary_top",
                         "type":"float",
                         "value":750
                        }, 
                        {
                         "name":"change_y",
                         "type":"float",
                         "value":0.75
                        }],
                 "rotation":0,
                 "type":"",
                 "visible":true,
                 "width":128,
                 "x":1150.81481481481,
                 "y":2349.18518518518
                }, 
                {
                 "gid":143,
                 "height":128,
                 "id":23,
                 "name":"",
                 "properties":[
                        {
                         "name":"boundary_bottom",
                         "type":"float",
                         "value":5
                        }, 
                        {
                         "name":"boundary_top",
                         "type":"float",
                         "value":750
                        }, 
                        {
                         "name":"change_y",
                         "type":"float",
                         "value":1
                        }],
                 "rotation":0,
                 "type":"",
                 "visible":true,
                 "width":128,
                 "x":1539.7037037037,
                 "y":1918.90383682072
                }, 
                {
                 "gid":143,
                 "height":128,
                 "id":24,
                 "name":"",
                 "properties":[
                        {
                         "name":"boundary_bottom",
                         "type":"float",
                         "value":5
                        }, 
                        {
                         "name":"boundary_top",
                         "type":"float",
                         "value":750
                        }, 
                        {
                         "name":"change_y",
                         "type":"float",
                         "value":1
                        }],
                 "rotation":0,
                 "type":"",
                 "visible":true,
                 "width":128,
                 "x":1880.00210768612,
                 "y":1385.58298320784
                }, 
                {
                 "gid":143,
                 "height":128,
                 "id":25,
                 "name":"",
                 "properties":[
                        {
                         "name":"boundary_bottom",
                         "type":"float",
                         "value":5
                        }, 
                        {
                         "name":"boundary_top",
                         "type":"float",
                         "value":750
                        }, 
                        {
                         "name":"change_y",
                         "type":"float",
                         "value":0.8
                        }],
                 "rotation":0,
                 "type":"",
                 "visible":true,
                 "width":128,
                 "x":2235.31638864623,
                 "y":1791.65090061983
                }, 
                {
                 "gid":143,
                 "height":128,
                 "id":26,
                 "name":"",
                 "properties":[
                        {
                         "name":"boundary_bottom",
                         "type":"float",
                         "value":5
                        }, 
                        {
                         "name":"boundary_top",
                         "type":"float",
                         "value":750
                        }, 
                        {
                         "name":"change_y",
                         "type":"float",
                         "value":0.9
                        }],
                 "rotation":0,
                 "type":"",
                 "visible":true,
                 "width":128,
                 "x":2498.96296296296,
                 "y":2308.44444444444
                }],
         "opacity":1,
         "type":"objectgroup",
         "visible":true,
         "x":0,
         "y":0
        }, 
        {
         "data":[0, 0, 0, 0, 0, 0, 0, 0, 0, 0, 0, 0, 0, 0, 0, 0, 0, 0, 0, 0, 0, 0, 0, 0, 0,
            0, 0, 0, 0, 0, 0, 0, 0, 0, 0, 0, 0, 0, 0, 0, 0, 0, 0, 0, 0, 0, 157, 0, 0, 0,
            0, 0, 0, 0, 0, 0, 0, 0, 0, 0, 0, 0, 0, 0, 0, 0, 0, 0, 0, 0, 0, 0, 0, 0, 0,
            0, 0, 0, 0, 0, 0, 0, 0, 0, 0, 0, 0, 0, 0, 0, 0, 0, 0, 0, 0, 0, 0, 0, 0, 0,
            0, 0, 0, 0, 0, 0, 0, 0, 0, 0, 0, 0, 0, 0, 0, 0, 0, 0, 0, 0, 0, 0, 0, 0, 0,
            0, 0, 0, 0, 0, 0, 0, 0, 0, 0, 0, 0, 0, 0, 0, 0, 0, 0, 0, 0, 0, 0, 0, 0, 0,
            0, 0, 0, 0, 0, 0, 0, 0, 0, 0, 0, 0, 0, 0, 0, 0, 0, 0, 0, 0, 0, 0, 0, 0, 0,
            0, 0, 0, 0, 0, 0, 0, 0, 0, 0, 0, 0, 0, 0, 0, 0, 0, 0, 0, 0, 0, 0, 0, 0, 0,
            0, 0, 0, 0, 0, 0, 0, 0, 0, 0, 0, 0, 0, 0, 0, 0, 0, 0, 0, 0, 0, 0, 0, 0, 0,
            0, 0, 0, 0, 0, 0, 0, 0, 0, 0, 0, 0, 0, 0, 0, 0, 0, 0, 0, 0, 0, 0, 0, 0, 0,
            0, 0, 0, 0, 0, 0, 0, 0, 0, 0, 0, 0, 0, 0, 0, 0, 0, 0, 0, 0, 0, 0, 0, 0, 0,
            0, 0, 0, 0, 0, 0, 0, 0, 0, 0, 0, 0, 0, 0, 0, 0, 0, 0, 0, 0, 0, 0, 0, 0, 0,
            0, 0, 0, 0, 0, 0, 0, 0, 0, 0, 0, 0, 0, 0, 0, 0, 0, 0, 0, 0, 0, 0, 0, 0, 0,
            0, 0, 0, 0, 0, 0, 0, 0, 0, 0, 0, 0, 0, 0, 0, 0, 0, 0, 0, 0, 0, 0, 0, 0, 0,
            0, 0, 0, 0, 0, 0, 0, 0, 0, 0, 0, 0, 0, 0, 0, 0, 0, 0, 0, 0, 0, 0, 0, 0, 0,
            0, 0, 0, 0, 0, 0, 0, 0, 0, 0, 0, 0, 0, 0, 0, 0, 0, 0, 0, 0, 0, 0, 0, 0, 0,
            0, 0, 0, 0, 0, 0, 0, 0, 0, 0, 0, 0, 0, 0, 0, 0, 0, 0, 0, 0, 0, 0, 0, 0, 0,
            0, 0, 0, 0, 0, 0, 0, 0, 0, 0, 0, 0, 0, 0, 0, 0, 0, 0, 0, 0, 0, 0, 0, 0, 0,
            0, 0, 0, 0, 0, 0, 0, 0, 0, 0, 0, 0, 0, 0, 0, 0, 0, 0, 0, 0, 0, 0, 0, 0, 0,
            0, 0, 0, 0, 0, 0, 0, 0, 0, 0, 0, 0, 0, 0, 0, 0, 0, 0, 0, 0, 0, 0, 0, 0, 0],
         "height":20,
         "id":8,
         "name":"Background",
         "opacity":1,
         "type":"tilelayer",
         "visible":true,
         "width":25,
         "x":0,
         "y":0
        }, 
        {
         "data":[0, 0, 0, 0, 0, 0, 0, 0, 0, 0, 0, 0, 0, 0, 0, 0, 0, 0, 0, 0, 0, 0, 0, 0, 0,
            0, 0, 0, 0, 0, 0, 0, 0, 0, 0, 0, 0, 0, 0, 0, 0, 0, 0, 0, 0, 0, 0, 0, 0, 0,
            0, 0, 0, 0, 0, 25, 0, 0, 0, 0, 0, 0, 0, 0, 0, 0, 0, 0, 0, 0, 0, 0, 0, 0, 0,
            0, 0, 0, 0, 0, 24, 0, 0, 0, 0, 0, 0, 0, 0, 0, 0, 0, 0, 0, 0, 0, 0, 0, 0, 0,
            0, 0, 0, 0, 0, 24, 0, 0, 0, 0, 0, 0, 0, 0, 0, 0, 0, 0, 0, 0, 0, 0, 0, 0, 0,
            0, 0, 0, 0, 0, 24, 0, 0, 0, 0, 0, 0, 0, 0, 0, 0, 0, 0, 0, 0, 0, 0, 0, 0, 0,
            0, 0, 0, 0, 0, 0, 0, 0, 0, 0, 0, 0, 0, 0, 0, 0, 0, 0, 0, 0, 0, 0, 0, 0, 0,
            0, 0, 0, 0, 0, 0, 0, 0, 0, 0, 0, 0, 0, 0, 0, 0, 0, 0, 0, 0, 0, 0, 0, 0, 0,
            0, 0, 0, 0, 0, 0, 0, 0, 0, 0, 0, 0, 0, 0, 0, 0, 0, 0, 0, 0, 0, 0, 0, 0, 0,
            0, 0, 0, 0, 0, 0, 0, 0, 0, 0, 0, 0, 0, 0, 0, 0, 0, 0, 0, 0, 0, 0, 0, 0, 0,
            0, 0, 0, 0, 0, 0, 0, 0, 0, 0, 0, 0, 0, 0, 0, 0, 0, 0, 0, 0, 0, 0, 0, 0, 0,
            0, 0, 0, 0, 0, 0, 0, 0, 0, 0, 0, 0, 0, 0, 0, 0, 0, 0, 0, 0, 0, 0, 0, 0, 0,
            0, 0, 0, 0, 0, 0, 0, 0, 0, 0, 0, 0, 0, 0, 0, 0, 0, 0, 0, 0, 0, 0, 0, 0, 0,
            0, 0, 0, 0, 0, 0, 0, 0, 0, 0, 0, 0, 0, 0, 0, 0, 0, 0, 0, 0, 0, 0, 0, 0, 0,
            0, 0, 0, 0, 0, 0, 0, 0, 0, 0, 0, 0, 0, 0, 0, 0, 0, 0, 0, 0, 0, 0, 0, 0, 0,
            0, 0, 0, 0, 0, 0, 0, 0, 0, 0, 0, 0, 0, 0, 0, 0, 0, 0, 0, 0, 0, 0, 0, 0, 0,
            0, 0, 0, 0, 0, 0, 0, 0, 0, 0, 0, 0, 0, 0, 0, 0, 0, 0, 0, 0, 0, 0, 0, 0, 0,
            0, 0, 0, 0, 0, 0, 0, 0, 0, 0, 0, 0, 0, 0, 0, 0, 0, 0, 0, 0, 0, 0, 0, 0, 0,
            0, 0, 0, 0, 0, 0, 0, 0, 0, 0, 0, 0, 0, 0, 0, 0, 0, 0, 0, 0, 0, 0, 0, 0, 0,
            0, 0, 0, 0, 0, 0, 0, 0, 0, 0, 0, 0, 0, 0, 0, 0, 0, 0, 0, 0, 0, 0, 0, 0, 0],
         "height":20,
         "id":9,
         "name":"Ladders",
         "opacity":1,
         "type":"tilelayer",
         "visible":true,
         "width":25,
         "x":0,
         "y":0
        }, 
        {
         "draworder":"topdown",
         "id":10,
         "name":"Coins",
         "objects":[
                {
                 "gid":98,
                 "height":128,
                 "id":7,
                 "name":"",
                 "properties":[
                        {
                         "name":"Points",
                         "type":"int",
                         "value":10
                        }],
                 "rotation":0,
                 "type":"",
                 "visible":true,
                 "width":128,
                 "x":1149.87283236994,
                 "y":1778.83622350674
                }, 
                {
                 "gid":98,
                 "height":128,
                 "id":9,
                 "name":"",
                 "properties":[
                        {
                         "name":"Points",
                         "type":"int",
                         "value":10
                        }],
                 "rotation":0,
                 "type":"",
                 "visible":true,
                 "width":128,
                 "x":1868.51591358275,
                 "y":1268.74908322456
                }],
         "opacity":1,
         "type":"objectgroup",
         "visible":true,
         "x":0,
         "y":0
        }, 
        {
         "data":[0, 0, 0, 0, 0, 0, 0, 0, 0, 0, 0, 0, 0, 0, 0, 0, 0, 0, 0, 0, 0, 0, 0, 0, 0,
            0, 0, 0, 0, 0, 0, 0, 0, 0, 0, 0, 0, 0, 0, 0, 0, 0, 0, 0, 0, 0, 0, 0, 0, 0,
            0, 0, 0, 0, 0, 0, 0, 0, 0, 0, 0, 0, 0, 0, 0, 0, 0, 0, 0, 0, 0, 0, 0, 0, 0,
            0, 0, 0, 0, 0, 0, 0, 0, 0, 0, 0, 0, 0, 0, 0, 0, 0, 0, 0, 0, 0, 0, 0, 0, 0,
            0, 0, 0, 0, 0, 0, 0, 0, 0, 0, 0, 0, 0, 0, 0, 0, 0, 0, 0, 0, 0, 0, 0, 0, 0,
            0, 0, 0, 0, 0, 0, 0, 0, 0, 0, 0, 0, 0, 0, 0, 0, 0, 0, 0, 0, 0, 0, 0, 0, 0,
            0, 0, 0, 0, 0, 0, 0, 0, 0, 0, 0, 0, 0, 0, 0, 0, 0, 0, 0, 0, 0, 0, 0, 0, 0,
            0, 0, 0, 0, 0, 0, 0, 0, 0, 0, 0, 0, 0, 0, 0, 0, 0, 0, 0, 0, 0, 0, 0, 0, 0,
            0, 0, 0, 0, 0, 0, 0, 0, 0, 0, 0, 0, 0, 0, 0, 0, 0, 0, 0, 0, 0, 0, 0, 0, 0,
            0, 0, 0, 0, 0, 0, 0, 0, 0, 0, 0, 0, 0, 0, 0, 0, 0, 0, 0, 0, 0, 0, 0, 0, 0,
            0, 0, 0, 0, 0, 0, 0, 0, 0, 0, 0, 0, 0, 0, 0, 0, 0, 0, 0, 0, 0, 0, 0, 0, 0,
            0, 0, 0, 0, 0, 0, 0, 0, 0, 0, 0, 0, 0, 0, 0, 0, 0, 0, 0, 0, 0, 0, 0, 0, 0,
            0, 0, 0, 0, 0, 0, 0, 0, 0, 0, 0, 0, 0, 0, 0, 0, 0, 0, 0, 0, 0, 0, 0, 0, 0,
            0, 0, 0, 0, 0, 0, 0, 0, 0, 0, 0, 0, 0, 0, 0, 0, 0, 0, 0, 0, 0, 0, 0, 0, 0,
            0, 0, 0, 0, 0, 0, 0, 0, 0, 0, 0, 0, 0, 0, 0, 0, 0, 0, 0, 0, 0, 0, 0, 0, 0,
            0, 0, 0, 0, 0, 0, 0, 0, 0, 0, 0, 0, 0, 0, 0, 0, 0, 0, 0, 0, 0, 0, 0, 0, 0,
            0, 0, 0, 0, 0, 0, 0, 0, 0, 0, 0, 0, 0, 0, 0, 0, 0, 0, 0, 0, 0, 0, 0, 0, 0,
            0, 0, 0, 0, 0, 0, 0, 0, 0, 0, 0, 0, 0, 0, 0, 0, 0, 0, 0, 0, 0, 0, 0, 0, 0,
            0, 0, 0, 0, 0, 0, 0, 0, 0, 0, 0, 0, 0, 0, 0, 0, 0, 0, 0, 0, 0, 0, 0, 0, 0,
            0, 0, 0, 0, 0, 0, 0, 0, 0, 0, 0, 0, 0, 0, 0, 0, 0, 0, 0, 0, 0, 0, 0, 0, 0],
         "height":20,
         "id":13,
         "name":"Interactive",
         "opacity":1,
         "type":"tilelayer",
         "visible":true,
         "width":25,
         "x":0,
         "y":0
        }],
 "nextlayerid":14,
 "nextobjectid":28,
 "orientation":"orthogonal",
 "renderorder":"right-down",
 "tiledversion":"1.10.2",
 "tileheight":128,
 "tilesets":[
        {
         "columns":0,
         "firstgid":1,
         "grid":
            {
             "height":1,
             "orientation":"orthogonal",
             "width":1
            },
         "margin":0,
         "name":"arcade_platformer",
         "spacing":0,
         "tilecount":78,
         "tileheight":128,
         "tiles":[
                {
                 "id":0,
                 "image":"..\/images\/ground\/Grass\/grass.png",
                 "imageheight":128,
                 "imagewidth":128
                }, 
                {
                 "id":1,
                 "image":"..\/images\/ground\/Grass\/grassCenter_round.png",
                 "imageheight":128,
                 "imagewidth":128
                }, 
                {
                 "id":2,
                 "image":"..\/images\/ground\/Grass\/grassCenter.png",
                 "imageheight":128,
                 "imagewidth":128
                }, 
                {
                 "id":3,
                 "image":"..\/images\/ground\/Grass\/grassCliff_left.png",
                 "imageheight":128,
                 "imagewidth":128
                }, 
                {
                 "id":4,
                 "image":"..\/images\/ground\/Grass\/grassCliff_right.png",
                 "imageheight":128,
                 "imagewidth":128
                }, 
                {
                 "id":5,
                 "image":"..\/images\/ground\/Grass\/grassCliffAlt_left.png",
                 "imageheight":128,
                 "imagewidth":128
                }, 
                {
                 "id":6,
                 "image":"..\/images\/ground\/Grass\/grassCliffAlt_right.png",
                 "imageheight":128,
                 "imagewidth":128
                }, 
                {
                 "id":7,
                 "image":"..\/images\/ground\/Grass\/grassCorner_left.png",
                 "imageheight":128,
                 "imagewidth":128
                }, 
                {
                 "id":8,
                 "image":"..\/images\/ground\/Grass\/grassCorner_right.png",
                 "imageheight":128,
                 "imagewidth":128
                }, 
                {
                 "id":9,
                 "image":"..\/images\/ground\/Grass\/grassHalf_left.png",
                 "imageheight":128,
                 "imagewidth":128
                }, 
                {
                 "id":10,
                 "image":"..\/images\/ground\/Grass\/grassHalf_mid.png",
                 "imageheight":128,
                 "imagewidth":128
                }, 
                {
                 "id":11,
                 "image":"..\/images\/ground\/Grass\/grassHalf_right.png",
                 "imageheight":128,
                 "imagewidth":128
                }, 
                {
                 "id":12,
                 "image":"..\/images\/ground\/Grass\/grassHalf.png",
                 "imageheight":128,
                 "imagewidth":128
                }, 
                {
                 "id":13,
                 "image":"..\/images\/ground\/Grass\/grassHill_left.png",
                 "imageheight":128,
                 "imagewidth":128
                }, 
                {
                 "id":14,
                 "image":"..\/images\/ground\/Grass\/grassHill_right.png",
                 "imageheight":128,
                 "imagewidth":128
                }, 
                {
                 "id":15,
                 "image":"..\/images\/ground\/Grass\/grassLeft.png",
                 "imageheight":128,
                 "imagewidth":128
                }, 
                {
                 "id":16,
                 "image":"..\/images\/ground\/Grass\/grassMid.png",
                 "imageheight":128,
                 "imagewidth":128
                }, 
                {
                 "id":17,
                 "image":"..\/images\/ground\/Grass\/grassRight.png",
                 "imageheight":128,
                 "imagewidth":128
                }, 
                {
                 "id":18,
                 "image":"..\/images\/items\/coinBronze.png",
                 "imageheight":128,
                 "imagewidth":128
                }, 
                {
                 "id":19,
                 "image":"..\/images\/items\/coinGold.png",
                 "imageheight":128,
                 "imagewidth":128
                }, 
                {
                 "id":20,
                 "image":"..\/images\/items\/coinSilver.png",
                 "imageheight":128,
                 "imagewidth":128
                }, 
                {
                 "id":21,
                 "image":"..\/images\/tiles\/doorOpen_mid.png",
                 "imageheight":128,
                 "imagewidth":128
                }, 
                {
                 "id":22,
                 "image":"..\/images\/tiles\/doorOpen_top.png",
                 "imageheight":128,
                 "imagewidth":128
                }, 
                {
                 "id":23,
                 "image":"..\/images\/tiles\/ladderMid.png",
                 "imageheight":128,
                 "imagewidth":128
                }, 
                {
                 "id":24,
                 "image":"..\/images\/tiles\/ladderTop.png",
                 "imageheight":128,
                 "imagewidth":128
                },
            
                {
                 "id":25,
                 "image":"..\/images\/items\/gemBlue.png",
                 "imageheight":128,
                 "imagewidth":128
                }, 
                {
                 "id":26,
                 "image":"..\/images\/items\/gemRed.png",
                 "imageheight":128,
                 "imagewidth":128
                }, 
                {
                 "id":27,
                 "image":"..\/images\/ground\/Planet\/planet.png",
                 "imageheight":128,
                 "imagewidth":128
                }, 
                {
                 "id":28,
                 "image":"..\/images\/ground\/Planet\/planetCenter_rounded.png",
                 "imageheight":128,
                 "imagewidth":128
                }, 
                {
                 "id":29,
                 "image":"..\/images\/ground\/Planet\/planetCenter.png",
                 "imageheight":128,
                 "imagewidth":128
                }, 
                {
                 "id":30,
                 "image":"..\/images\/ground\/Planet\/planetCliff_left.png",
                 "imageheight":128,
                 "imagewidth":128
                }, 
                {
                 "id":31,
                 "image":"..\/images\/ground\/Planet\/planetCliff_right.png",
                 "imageheight":128,
                 "imagewidth":128
                }, 
                {
                 "id":32,
                 "image":"..\/images\/ground\/Planet\/planetCliffAlt_left.png",
                 "imageheight":128,
                 "imagewidth":128
                }, 
                {
                 "id":33,
                 "image":"..\/images\/ground\/Planet\/planetCliffAlt_right.png",
                 "imageheight":128,
                 "imagewidth":128
                }, 
                {
                 "id":34,
                 "image":"..\/images\/ground\/Planet\/planetCorner_left.png",
                 "imageheight":128,
                 "imagewidth":128
                }, 
                {
                 "id":35,
                 "image":"..\/images\/ground\/Planet\/planetCorner_right.png",
                 "imageheight":128,
                 "imagewidth":128
                }, 
                {
                 "id":36,
                 "image":"..\/images\/ground\/Planet\/planetHalf_left.png",
                 "imageheight":128,
                 "imagewidth":128
                }, 
                {
                 "id":37,
                 "image":"..\/images\/ground\/Planet\/planetHalf_mid.png",
                 "imageheight":128,
                 "imagewidth":128
                }, 
                {
                 "id":38,
                 "image":"..\/images\/ground\/Planet\/planetHalf_right.png",
                 "imageheight":128,
                 "imagewidth":128
                }, 
                {
                 "id":39,
                 "image":"..\/images\/ground\/Planet\/planetHalf.png",
                 "imageheight":128,
                 "imagewidth":128
                }, 
                {
                 "id":40,
                 "image":"..\/images\/ground\/Planet\/planetHill_left.png",
                 "imageheight":128,
                 "imagewidth":128
                }, 
                {
                 "id":41,
                 "image":"..\/images\/ground\/Planet\/planetHill_right.png",
                 "imageheight":128,
                 "imagewidth":128
                }, 
                {
                 "id":42,
                 "image":"..\/images\/ground\/Planet\/planetLeft.png",
                 "imageheight":128,
                 "imagewidth":128
                }, 
                {
                 "id":43,
                 "image":"..\/images\/ground\/Planet\/planetMid.png",
                 "imageheight":128,
                 "imagewidth":128
                }, 
                {
                 "id":44,
                 "image":"..\/images\/ground\/Planet\/planetRight.png",
                 "imageheight":128,
                 "imagewidth":128
                }, 
                {
                 "id":45,
                 "image":"..\/images\/tiles\/torch1.png",
                 "imageheight":128,
                 "imagewidth":128
                }, 
                {
                 "id":46,
                 "image":"..\/images\/tiles\/torch2.png",
                 "imageheight":128,
                 "imagewidth":128
                }, 
                {
                 "id":47,
                 "image":"..\/images\/tiles\/lava.png",
                 "imageheight":128,
                 "imagewidth":128
                }, 
                {
                 "id":48,
                 "image":"..\/images\/tiles\/lavaTop_high.png",
                 "imageheight":128,
                 "imagewidth":128
                }, 
                {
                 "id":49,
                 "image":"..\/images\/tiles\/lavaTop_low.png",
                 "imageheight":128,
                 "imagewidth":128
                },
            
                {
                 "id":50,
                 "image":"..\/images\/items\/star.png",
                 "imageheight":128,
                 "imagewidth":128
                }, 
                {
                 "id":51,
                 "image":"..\/images\/tiles\/spikes.png",
                 "imageheight":128,
                 "imagewidth":128
                }, 
                {
                 "id":52,
                 "image":"..\/images\/ground\/Snow\/snow.png",
                 "imageheight":128,
                 "imagewidth":128
                }, 
                {
                 "id":53,
                 "image":"..\/images\/ground\/Snow\/snowCenter_rounded.png",
                 "imageheight":128,
                 "imagewidth":128
                }, 
                {
                 "id":54,
                 "image":"..\/images\/ground\/Snow\/snowCenter.png",
                 "imageheight":128,
                 "imagewidth":128
                }, 
                {
                 "id":55,
                 "image":"..\/images\/ground\/Snow\/snowCliff_left.png",
                 "imageheight":128,
                 "imagewidth":128
                }, 
                {
                 "id":56,
                 "image":"..\/images\/ground\/Snow\/snowCliff_right.png",
                 "imageheight":128,
                 "imagewidth":128
                }, 
                {
                 "id":57,
                 "image":"..\/images\/ground\/Snow\/snowCliffAlt_left.png",
                 "imageheight":128,
                 "imagewidth":128
                }, 
                {
                 "id":58,
                 "image":"..\/images\/ground\/Snow\/snowCliffAlt_right.png",
                 "imageheight":128,
                 "imagewidth":128
                }, 
                {
                 "id":59,
                 "image":"..\/images\/ground\/Snow\/snowCorner_left.png",
                 "imageheight":128,
                 "imagewidth":128
                }, 
                {
                 "id":60,
                 "image":"..\/images\/ground\/Snow\/snowCorner_right.png",
                 "imageheight":128,
                 "imagewidth":128
                }, 
                {
                 "id":61,
                 "image":"..\/images\/ground\/Snow\/snowHalf_left.png",
                 "imageheight":128,
                 "imagewidth":128
                }, 
                {
                 "id":62,
                 "image":"..\/images\/ground\/Snow\/snowHalf_mid.png",
                 "imageheight":128,
                 "imagewidth":128
                }, 
                {
                 "id":63,
                 "image":"..\/images\/ground\/Snow\/snowHalf_right.png",
                 "imageheight":128,
                 "imagewidth":128
                }, 
                {
                 "id":64,
                 "image":"..\/images\/ground\/Snow\/snowHalf.png",
                 "imageheight":128,
                 "imagewidth":128
                }, 
                {
                 "id":65,
                 "image":"..\/images\/ground\/Snow\/snowHill_left.png",
                 "imageheight":128,
                 "imagewidth":128
                }, 
                {
                 "id":66,
                 "image":"..\/images\/ground\/Snow\/snowHill_right.png",
                 "imageheight":128,
                 "imagewidth":128
                }, 
                {
                 "id":67,
                 "image":"..\/images\/ground\/Snow\/snowLeft.png",
                 "imageheight":128,
                 "imagewidth":128
                }, 
                {
                 "id":68,
                 "image":"..\/images\/ground\/Snow\/snowMid.png",
                 "imageheight":128,
                 "imagewidth":128
                }, 
                {
                 "id":69,
                 "image":"..\/images\/ground\/Snow\/snowRight.png",
                 "imageheight":128,
                 "imagewidth":128
                }, 
                {
                 "id":70,
                 "image":"..\/images\/items\/flagGreen1.png",
                 "imageheight":128,
                 "imagewidth":128
                }, 
                {
                 "id":71,
                 "image":"..\/images\/items\/flagRed1.png",
                 "imageheight":128,
                 "imagewidth":128
                }, 
                {
                 "id":72,
                 "image":"..\/images\/items\/flagYellow1.png",
                 "imageheight":128,
                 "imagewidth":128
                }, 
                {
                 "id":73,
                 "image":"..\/images\/items\/gemGreen.png",
                 "imageheight":128,
                 "imagewidth":128
                }, 
                {
                 "id":74,
                 "image":"..\/images\/HUD\/hudHeart_full.png",
                 "imageheight":128,
                 "imagewidth":128
                },
            
                {
                 "id":75,
                 "image":"..\/images\/HUD\/hudHeart_half.png",
                 "imageheight":128,
                 "imagewidth":128
                }, 
                {
                 "id":76,
                 "image":"..\/images\/tiles\/mushroomRed.png",
                 "imageheight":128,
                 "imagewidth":128
                }, 
                {
                 "id":77,
                 "image":"..\/images\/tiles\/mushroomBrown.png",
                 "imageheight":128,
                 "imagewidth":128
                }],
         "tilewidth":128
        }, 
        {
         "firstgid":79,
         "source":"arcade_platformer.tsj"
        }],
 "tilewidth":128,
 "type":"map",
 "version":"1.10",
 "width":25
}